setup.cfg
setup.py
carl/__init__.py
carl/carl.py
carl/utils.py
carl.egg-info/PKG-INFO
carl.egg-info/SOURCES.txt
carl.egg-info/dependency_links.txt
carl.egg-info/requires.txt
carl.egg-info/top_level.txt