Metadata-Version: 1.1
Name: carl
Version: 0.0.4
Summary: An entry-point library based on argparse, to make creating cli tools as easy as possible.
Home-page: https://gitlab.com/tarcisioe/carl
Author: Tarcísio Eduardo Moreira Crocomo
Author-email: tarcisio.crocomo+pypi@gmail.com
License: UNKNOWN
Download-URL: https://gitlab.com/tarcisioe/carl/repository/archive.tar.gz?ref=0.0.4
Keywords: entry,points,subcommands
Platform: UNKNOWN
Classifier: Programming Language :: Python
Classifier: Programming Language :: Python :: 3
Classifier: Programming Language :: Python :: 3.6
